v_palette/__init__.py
v_palette/colors.py
v_palette/palette.py
v_palette-1.1.0.dist-info/LICENSE.txt
v_palette-1.1.0.dist-info/METADATA
v_palette-1.1.0.dist-info/WHEEL
v_palette-1.1.0.dist-info/top_level.txt
v_palette-1.1.0.dist-info/RECORD
