Metadata-Version: 2.1
Name: v-palette
Version: 1.1.0
Summary: Utility to easily use material design colors
Home-page: https://github.com/villoro/v-palette
Author: Arnau Villoro
Author-email: arnau@villoro.com
License: MIT
Platform: UNKNOWN
Classifier: Intended Audience :: Developers
Classifier: Intended Audience :: Education
Classifier: Intended Audience :: Manufacturing
Classifier: Intended Audience :: Science/Research
Classifier: License :: OSI Approved :: MIT License
Classifier: Programming Language :: Python
Classifier: Programming Language :: Python :: 3.6
